<?xml version="1.0" encoding="UTF-8"?>
<conduit>
  <hdr>
    <ver>2.0</ver>
    <rqid>01234567890</rqid>
    <authn u="user" p="password"/>
    <txndtrng bdt="2013-09-01" edt="2013-09-30"/>
    <parse>ftrue</parse>
  </hdr>
  <complst>
    <comp uid="testCompany-1" puid="ROOT">
      <tp>processor</tp>
      <busn>
        <nm>Test Business Name &amp; 1</nm>
      </busn>
      <acctprodlst>
        <acctprod uid="testAccProductId1-1" del = "t">
          <ac>a</ac>
          <nm>TestAccountProductName1-1</nm> 
        </acctprod>
        <acctprod uid="testAccProductId1-2" del = "1">
          <ac>a</ac>
          <nm>TestAccountProductName1-2</nm> 
        </acctprod>
        <acctprod uid="testAccProductId1-3" del = "true">
          <ac>a</ac>
          <nm>TestAccountProductName1-3</nm> 
        </acctprod>
        <acctprod uid="testAccProductId1-4" del = "true">
          <ac>a</ac>
          <nm>TestAccountProductName1-4</nm>
        </acctprod>
      </acctprodlst>
      <alst>
      	<a n="TestProductAttribute1-1" t = "datetime"  d = "1">TestProductAttribute1-1</a>
      </alst>
    </comp>
    <comp uid="testCompany-2" puid="testCompany-1">
      <tp>holding</tp>
      <busn>
        <nm>Test Business Name - 2</nm>
      </busn>
      <acctprodlst>
        <acctprod uid="testAccProductId2-1" del = "true">
          <ac>a</ac>
          <nm>TestAccountProductName2-1</nm>
          <alst>
                <a	n = "ACHTransferFrom2-1" 	t = "string" 	d = "1">2014-04-02</a>
          </alst>  
        </acctprod>
      </acctprodlst>
    </comp>
   </complst>
</conduit>
